{
    "pj washington": {
        "min": 35,
        "fgm": 5,
        "fga": 13,
        "3ptm": 3,
        "3pta": 4,
        "ftm": 1,
        "fta": 2,
        "oreb": 1,
        "dreb": 8,
        "reb": 9,
        "ast": 0,
        "stl": 2,
        "blk": 1,
        "to": 2,
        "pf": 3,
        "+/-": -13,
        "pts": 14
    },
    "dereck lively": {
        "min": 28,
        "fgm": 5,
        "fga": 5,
        "3ptm": 0,
        "3pta": 0,
        "ftm": 3,
        "fta": 4,
        "oreb": 1,
        "dreb": 6,
        "reb": 7,
        "ast": 2,
        "stl": 0,
        "blk": 3,
        "to": 2,
        "pf": 4,
        "+/-": -3,
        "pts": 13
    },
    "spencer dinwiddie": {
        "min": 37,
        "fgm": 6,
        "fga": 16,
        "3ptm": 0,
        "3pta": 6,
        "ftm": 7,
        "fta": 9,
        "oreb": 1,
        "dreb": 2,
        "reb": 3,
        "ast": 7,
        "stl": 3,
        "blk": 1,
        "to": 1,
        "pf": 0,
        "+/-": -17,
        "pts": 19
    },
    "klay thompson": {
        "min": 30,
        "fgm": 9,
        "fga": 17,
        "3ptm": 2,
        "3pta": 9,
        "ftm": 2,
        "fta": 2,
        "oreb": 1,
        "dreb": 2,
        "reb": 3,
        "ast": 3,
        "stl": 2,
        "blk": 0,
        "to": 4,
        "pf": 0,
        "+/-": -2,
        "pts": 22
    },
    "quentin grimes": {
        "min": 28,
        "fgm": 3,
        "fga": 8,
        "3ptm": 1,
        "3pta": 4,
        "ftm": 4,
        "fta": 5,
        "oreb": 0,
        "dreb": 5,
        "reb": 5,
        "ast": 3,
        "stl": 1,
        "blk": 0,
        "to": 1,
        "pf": 2,
        "+/-": -22,
        "pts": 11
    },
    "markieff morris": {
        "min": 3,
        "fgm": 0,
        "fga": 0,
        "3ptm": 0,
        "3pta": 0,
        "ftm": 0,
        "fta": 0,
        "oreb": 0,
        "dreb": 0,
        "reb": 0,
        "ast": 0,
        "stl": 0,
        "blk": 0,
        "to": 0,
        "pf": 0,
        "+/-": -6,
        "pts": 0
    },
    "maxi kleber": {
        "min": 13,
        "fgm": 0,
        "fga": 1,
        "3ptm": 0,
        "3pta": 0,
        "ftm": 0,
        "fta": 0,
        "oreb": 1,
        "dreb": 1,
        "reb": 2,
        "ast": 0,
        "stl": 0,
        "blk": 0,
        "to": 0,
        "pf": 0,
        "+/-": -6,
        "pts": 0
    },
    "olivier maxence prosper": {
        "min": 11,
        "fgm": 0,
        "fga": 3,
        "3ptm": 0,
        "3pta": 1,
        "ftm": 0,
        "fta": 0,
        "oreb": 0,
        "dreb": 0,
        "reb": 0,
        "ast": 1,
        "stl": 0,
        "blk": 0,
        "to": 0,
        "pf": 0,
        "+/-": -1,
        "pts": 0
    },
    "naji marshall": {
        "min": 24,
        "fgm": 4,
        "fga": 12,
        "3ptm": 1,
        "3pta": 4,
        "ftm": 0,
        "fta": 0,
        "oreb": 1,
        "dreb": 4,
        "reb": 5,
        "ast": 1,
        "stl": 1,
        "blk": 0,
        "to": 1,
        "pf": 1,
        "+/-": -15,
        "pts": 9
    },
    "kessler edwards": {
        "min": 3,
        "fgm": 0,
        "fga": 1,
        "3ptm": 0,
        "3pta": 1,
        "ftm": 0,
        "fta": 0,
        "oreb": 0,
        "dreb": 1,
        "reb": 1,
        "ast": 0,
        "stl": 0,
        "blk": 0,
        "to": 0,
        "pf": 0,
        "+/-": -6,
        "pts": 0
    },
    "dwight powell": {
        "min": 3,
        "fgm": 0,
        "fga": 0,
        "3ptm": 0,
        "3pta": 0,
        "ftm": 0,
        "fta": 0,
        "oreb": 0,
        "dreb": 0,
        "reb": 0,
        "ast": 0,
        "stl": 0,
        "blk": 0,
        "to": 0,
        "pf": 0,
        "+/-": -6,
        "pts": 0
    },
    "daniel gafford": {
        "min": 14,
        "fgm": 0,
        "fga": 4,
        "3ptm": 0,
        "3pta": 0,
        "ftm": 2,
        "fta": 4,
        "oreb": 2,
        "dreb": 2,
        "reb": 4,
        "ast": 2,
        "stl": 0,
        "blk": 0,
        "to": 1,
        "pf": 2,
        "+/-": -12,
        "pts": 2
    },
    "jazian gortman": {
        "min": 11,
        "fgm": 2,
        "fga": 6,
        "3ptm": 0,
        "3pta": 1,
        "ftm": 1,
        "fta": 2,
        "oreb": 0,
        "dreb": 1,
        "reb": 1,
        "ast": 2,
        "stl": 0,
        "blk": 0,
        "to": 1,
        "pf": 1,
        "+/-": -6,
        "pts": 5
    }
}