{
    "oskar back": {
        "g": 0.0,
        "a": 0.0,
        "+/-": 0.0,
        "s": 0.0,
        "sm": 0.0,
        "bs": 1.0,
        "pn": 0.0,
        "pim": 0.0,
        "ht": 2.0,
        "tk": 2.0,
        "gv": 0.0,
        "shft": 25.0,
        "toi": 18.35,
        "pptoi": 0.0,
        "shtoi": 2.32,
        "estoi": 16.03,
        "fw": 3.0,
        "fl": 1.0,
        "fo%": 75.0
    },
    "jamie benn": {
        "g": 0.0,
        "a": 0.0,
        "+/-": 0.0,
        "s": 1.0,
        "sm": 1.0,
        "bs": 1.0,
        "pn": 0.0,
        "pim": 0.0,
        "ht": 2.0,
        "tk": 0.0,
        "gv": 0.0,
        "shft": 21.0,
        "toi": 15.88,
        "pptoi": 0.37,
        "shtoi": 0.33,
        "estoi": 15.18,
        "fw": 1.0,
        "fl": 2.0,
        "fo%": 33.3
    },
    "colin blackwell": {
        "g": 0.0,
        "a": 1.0,
        "+/-": 1.0,
        "s": 4.0,
        "sm": 0.0,
        "bs": 0.0,
        "pn": 0.0,
        "pim": 0.0,
        "ht": 1.0,
        "tk": 0.0,
        "gv": 0.0,
        "shft": 17.0,
        "toi": 13.48,
        "pptoi": 0.0,
        "shtoi": 2.98,
        "estoi": 10.5,
        "fw": 5.0,
        "fl": 5.0,
        "fo%": 50.0
    },
    "matej blumel": {
        "g": 1.0,
        "a": 0.0,
        "+/-": 1.0,
        "s": 2.0,
        "sm": 0.0,
        "bs": 0.0,
        "pn": 0.0,
        "pim": 0.0,
        "ht": 1.0,
        "tk": 0.0,
        "gv": 1.0,
        "shft": 12.0,
        "toi": 9.35,
        "pptoi": 0.0,
        "shtoi": 0.0,
        "estoi": 9.35,
        "fw": 0.0,
        "fl": 0.0,
        "fo%": 0.0
    },
    "mavrik bourque": {
        "g": 1.0,
        "a": 0.0,
        "+/-": 1.0,
        "s": 1.0,
        "sm": 1.0,
        "bs": 0.0,
        "pn": 0.0,
        "pim": 0.0,
        "ht": 2.0,
        "tk": 0.0,
        "gv": 1.0,
        "shft": 19.0,
        "toi": 13.82,
        "pptoi": 0.0,
        "shtoi": 0.17,
        "estoi": 13.65,
        "fw": 4.0,
        "fl": 1.0,
        "fo%": 80.0
    },
    "evgenii dadonov": {
        "g": 0.0,
        "a": 0.0,
        "+/-": 0.0,
        "s": 1.0,
        "sm": 1.0,
        "bs": 1.0,
        "pn": 1.0,
        "pim": 2.0,
        "ht": 1.0,
        "tk": 1.0,
        "gv": 1.0,
        "shft": 23.0,
        "toi": 13.67,
        "pptoi": 0.0,
        "shtoi": 0.0,
        "estoi": 13.67,
        "fw": 0.0,
        "fl": 0.0,
        "fo%": 0.0
    },
    "matt duchene": {
        "g": 0.0,
        "a": 2.0,
        "+/-": 1.0,
        "s": 3.0,
        "sm": 1.0,
        "bs": 0.0,
        "pn": 0.0,
        "pim": 0.0,
        "ht": 1.0,
        "tk": 1.0,
        "gv": 1.0,
        "shft": 20.0,
        "toi": 15.45,
        "pptoi": 0.37,
        "shtoi": 0.0,
        "estoi": 15.08,
        "fw": 4.0,
        "fl": 6.0,
        "fo%": 40.0
    },
    "justin hryckowian": {
        "g": 0.0,
        "a": 1.0,
        "+/-": 1.0,
        "s": 1.0,
        "sm": 0.0,
        "bs": 0.0,
        "pn": 0.0,
        "pim": 0.0,
        "ht": 2.0,
        "tk": 0.0,
        "gv": 0.0,
        "shft": 15.0,
        "toi": 10.03,
        "pptoi": 0.0,
        "shtoi": 0.0,
        "estoi": 10.03,
        "fw": 2.0,
        "fl": 2.0,
        "fo%": 50.0
    },
    "wyatt johnston": {
        "g": 1.0,
        "a": 0.0,
        "+/-": 0.0,
        "s": 1.0,
        "sm": 0.0,
        "bs": 0.0,
        "pn": 0.0,
        "pim": 0.0,
        "ht": 2.0,
        "tk": 1.0,
        "gv": 0.0,
        "shft": 23.0,
        "toi": 16.67,
        "pptoi": 0.37,
        "shtoi": 1.48,
        "estoi": 14.82,
        "fw": 7.0,
        "fl": 2.0,
        "fo%": 77.8
    },
    "jason robertson": {
        "g": 1.0,
        "a": 1.0,
        "+/-": 1.0,
        "s": 2.0,
        "sm": 2.0,
        "bs": 0.0,
        "pn": 0.0,
        "pim": 0.0,
        "ht": 0.0,
        "tk": 0.0,
        "gv": 2.0,
        "shft": 22.0,
        "toi": 15.25,
        "pptoi": 0.37,
        "shtoi": 0.0,
        "estoi": 14.88,
        "fw": 0.0,
        "fl": 1.0,
        "fo%": 0.0
    },
    "logan stankoven": {
        "g": 0.0,
        "a": 0.0,
        "+/-": 0.0,
        "s": 2.0,
        "sm": 1.0,
        "bs": 1.0,
        "pn": 0.0,
        "pim": 0.0,
        "ht": 1.0,
        "tk": 0.0,
        "gv": 1.0,
        "shft": 20.0,
        "toi": 15.9,
        "pptoi": 0.0,
        "shtoi": 0.0,
        "estoi": 15.9,
        "fw": 5.0,
        "fl": 4.0,
        "fo%": 55.6
    },
    "sam steel": {
        "g": 0.0,
        "a": 0.0,
        "+/-": 0.0,
        "s": 3.0,
        "sm": 1.0,
        "bs": 0.0,
        "pn": 0.0,
        "pim": 0.0,
        "ht": 1.0,
        "tk": 0.0,
        "gv": 0.0,
        "shft": 22.0,
        "toi": 17.43,
        "pptoi": 0.0,
        "shtoi": 1.98,
        "estoi": 15.45,
        "fw": 7.0,
        "fl": 2.0,
        "fo%": 77.8
    },
    "thomas harley": {
        "g": 0.0,
        "a": 0.0,
        "+/-": 1.0,
        "s": 1.0,
        "sm": 0.0,
        "bs": 1.0,
        "pn": 0.0,
        "pim": 0.0,
        "ht": 0.0,
        "tk": 1.0,
        "gv": 2.0,
        "shft": 26.0,
        "toi": 22.5,
        "pptoi": 0.0,
        "shtoi": 1.52,
        "estoi": 20.98,
        "fw": 0.0,
        "fl": 0.0,
        "fo%": 0.0
    },
    "miro heiskanen": {
        "g": 0.0,
        "a": 1.0,
        "+/-": -1.0,
        "s": 2.0,
        "sm": 1.0,
        "bs": 2.0,
        "pn": 0.0,
        "pim": 0.0,
        "ht": 0.0,
        "tk": 1.0,
        "gv": 3.0,
        "shft": 27.0,
        "toi": 21.33,
        "pptoi": 0.37,
        "shtoi": 0.82,
        "estoi": 20.15,
        "fw": 0.0,
        "fl": 0.0,
        "fo%": 0.0
    },
    "esa lindell": {
        "g": 0.0,
        "a": 0.0,
        "+/-": 0.0,
        "s": 0.0,
        "sm": 0.0,
        "bs": 3.0,
        "pn": 0.0,
        "pim": 0.0,
        "ht": 1.0,
        "tk": 0.0,
        "gv": 1.0,
        "shft": 25.0,
        "toi": 23.92,
        "pptoi": 0.0,
        "shtoi": 3.82,
        "estoi": 20.1,
        "fw": 0.0,
        "fl": 0.0,
        "fo%": 0.0
    },
    "nils lundkvist": {
        "g": 0.0,
        "a": 0.0,
        "+/-": 1.0,
        "s": 0.0,
        "sm": 1.0,
        "bs": 1.0,
        "pn": 1.0,
        "pim": 2.0,
        "ht": 2.0,
        "tk": 0.0,
        "gv": 1.0,
        "shft": 25.0,
        "toi": 15.92,
        "pptoi": 0.0,
        "shtoi": 0.0,
        "estoi": 15.92,
        "fw": 0.0,
        "fl": 0.0,
        "fo%": 0.0
    },
    "ilya lyubushkin": {
        "g": 0.0,
        "a": 1.0,
        "+/-": 2.0,
        "s": 0.0,
        "sm": 0.0,
        "bs": 4.0,
        "pn": 0.0,
        "pim": 0.0,
        "ht": 0.0,
        "tk": 0.0,
        "gv": 2.0,
        "shft": 26.0,
        "toi": 20.55,
        "pptoi": 0.0,
        "shtoi": 3.12,
        "estoi": 17.43,
        "fw": 0.0,
        "fl": 0.0,
        "fo%": 0.0
    },
    "brendan smith": {
        "g": 0.0,
        "a": 0.0,
        "+/-": 1.0,
        "s": 1.0,
        "sm": 0.0,
        "bs": 0.0,
        "pn": 1.0,
        "pim": 2.0,
        "ht": 0.0,
        "tk": 0.0,
        "gv": 4.0,
        "shft": 22.0,
        "toi": 16.03,
        "pptoi": 0.0,
        "shtoi": 0.0,
        "estoi": 16.03,
        "fw": 0.0,
        "fl": 0.0,
        "fo%": 0.0
    },
    "jake oettinger": {
        "sa": 34.0,
        "ga": 1.0,
        "sv": 33.0,
        "sv%": 0.971,
        "essv": 27.0,
        "ppsv": 6.0,
        "shsv": 0.0,
        "sosa": 0.0,
        "sos": 0.0,
        "toi": 59.83,
        "pim": 0.0
    }
}