{
    "mikael backlund": {
        "g": 0.0,
        "a": 0.0,
        "+/-": 0.0,
        "s": 1.0,
        "sm": 1.0,
        "bs": 0.0,
        "pn": 1.0,
        "pim": 2.0,
        "ht": 0.0,
        "tk": 0.0,
        "gv": 1.0,
        "shft": 28.0,
        "toi": 22.18,
        "pptoi": 3.37,
        "shtoi": 2.17,
        "estoi": 16.65,
        "fw": 10.0,
        "fl": 15.0,
        "fo%": 40.0
    },
    "blake coleman": {
        "g": 0.0,
        "a": 2.0,
        "+/-": 2.0,
        "s": 2.0,
        "sm": 1.0,
        "bs": 0.0,
        "pn": 0.0,
        "pim": 0.0,
        "ht": 5.0,
        "tk": 1.0,
        "gv": 1.0,
        "shft": 25.0,
        "toi": 21.9,
        "pptoi": 3.13,
        "shtoi": 3.1,
        "estoi": 15.67,
        "fw": 0.0,
        "fl": 0.0,
        "fo%": 0.0
    },
    "matt coronato": {
        "g": 0.0,
        "a": 0.0,
        "+/-": -1.0,
        "s": 1.0,
        "sm": 1.0,
        "bs": 0.0,
        "pn": 0.0,
        "pim": 0.0,
        "ht": 2.0,
        "tk": 0.0,
        "gv": 2.0,
        "shft": 16.0,
        "toi": 13.18,
        "pptoi": 3.2,
        "shtoi": 0.4,
        "estoi": 9.58,
        "fw": 0.0,
        "fl": 1.0,
        "fo%": 0.0
    },
    "jonathan huberdeau": {
        "g": 0.0,
        "a": 0.0,
        "+/-": 1.0,
        "s": 1.0,
        "sm": 1.0,
        "bs": 0.0,
        "pn": 0.0,
        "pim": 0.0,
        "ht": 0.0,
        "tk": 0.0,
        "gv": 3.0,
        "shft": 25.0,
        "toi": 19.53,
        "pptoi": 4.18,
        "shtoi": 2.87,
        "estoi": 12.48,
        "fw": 0.0,
        "fl": 0.0,
        "fo%": 0.0
    },
    "nazem kadri": {
        "g": 1.0,
        "a": 0.0,
        "+/-": -1.0,
        "s": 2.0,
        "sm": 2.0,
        "bs": 0.0,
        "pn": 0.0,
        "pim": 0.0,
        "ht": 0.0,
        "tk": 0.0,
        "gv": 2.0,
        "shft": 25.0,
        "toi": 22.55,
        "pptoi": 4.18,
        "shtoi": 0.53,
        "estoi": 17.83,
        "fw": 9.0,
        "fl": 18.0,
        "fo%": 33.3
    },
    "justin kirkland": {
        "g": 0.0,
        "a": 1.0,
        "+/-": 1.0,
        "s": 0.0,
        "sm": 0.0,
        "bs": 2.0,
        "pn": 0.0,
        "pim": 0.0,
        "ht": 1.0,
        "tk": 0.0,
        "gv": 0.0,
        "shft": 21.0,
        "toi": 14.47,
        "pptoi": 0.42,
        "shtoi": 2.42,
        "estoi": 11.63,
        "fw": 5.0,
        "fl": 7.0,
        "fo%": 41.7
    },
    "adam klapka": {
        "g": 0.0,
        "a": 0.0,
        "+/-": 1.0,
        "s": 1.0,
        "sm": 0.0,
        "bs": 0.0,
        "pn": 0.0,
        "pim": 0.0,
        "ht": 3.0,
        "tk": 0.0,
        "gv": 1.0,
        "shft": 13.0,
        "toi": 6.92,
        "pptoi": 0.43,
        "shtoi": 0.0,
        "estoi": 6.48,
        "fw": 0.0,
        "fl": 0.0,
        "fo%": 0.0
    },
    "andrei kuzmenko": {
        "g": 0.0,
        "a": 0.0,
        "+/-": 0.0,
        "s": 2.0,
        "sm": 0.0,
        "bs": 1.0,
        "pn": 1.0,
        "pim": 2.0,
        "ht": 0.0,
        "tk": 0.0,
        "gv": 0.0,
        "shft": 22.0,
        "toi": 16.97,
        "pptoi": 4.43,
        "shtoi": 0.0,
        "estoi": 12.53,
        "fw": 0.0,
        "fl": 0.0,
        "fo%": 0.0
    },
    "ryan lomberg": {
        "g": 0.0,
        "a": 1.0,
        "+/-": 1.0,
        "s": 0.0,
        "sm": 0.0,
        "bs": 0.0,
        "pn": 0.0,
        "pim": 0.0,
        "ht": 2.0,
        "tk": 0.0,
        "gv": 0.0,
        "shft": 14.0,
        "toi": 8.18,
        "pptoi": 0.47,
        "shtoi": 1.58,
        "estoi": 6.13,
        "fw": 1.0,
        "fl": 1.0,
        "fo%": 50.0
    },
    "anthony mantha": {
        "g": 0.0,
        "a": 0.0,
        "+/-": 0.0,
        "s": 0.0,
        "sm": 2.0,
        "bs": 0.0,
        "pn": 0.0,
        "pim": 0.0,
        "ht": 1.0,
        "tk": 0.0,
        "gv": 0.0,
        "shft": 19.0,
        "toi": 16.73,
        "pptoi": 3.38,
        "shtoi": 0.0,
        "estoi": 13.35,
        "fw": 0.0,
        "fl": 1.0,
        "fo%": 0.0
    },
    "martin pospisil": {
        "g": 0.0,
        "a": 0.0,
        "+/-": 0.0,
        "s": 2.0,
        "sm": 0.0,
        "bs": 0.0,
        "pn": 2.0,
        "pim": 4.0,
        "ht": 2.0,
        "tk": 0.0,
        "gv": 0.0,
        "shft": 16.0,
        "toi": 10.37,
        "pptoi": 0.0,
        "shtoi": 0.0,
        "estoi": 10.37,
        "fw": 3.0,
        "fl": 4.0,
        "fo%": 42.9
    },
    "connor zary": {
        "g": 0.0,
        "a": 0.0,
        "+/-": 0.0,
        "s": 4.0,
        "sm": 1.0,
        "bs": 1.0,
        "pn": 0.0,
        "pim": 0.0,
        "ht": 1.0,
        "tk": 0.0,
        "gv": 0.0,
        "shft": 22.0,
        "toi": 19.47,
        "pptoi": 4.33,
        "shtoi": 0.0,
        "estoi": 15.13,
        "fw": 0.0,
        "fl": 1.0,
        "fo%": 0.0
    },
    "rasmus andersson": {
        "g": 1.0,
        "a": 1.0,
        "+/-": 1.0,
        "s": 3.0,
        "sm": 2.0,
        "bs": 4.0,
        "pn": 0.0,
        "pim": 0.0,
        "ht": 0.0,
        "tk": 1.0,
        "gv": 1.0,
        "shft": 32.0,
        "toi": 25.33,
        "pptoi": 3.18,
        "shtoi": 3.68,
        "estoi": 18.47,
        "fw": 0.0,
        "fl": 0.0,
        "fo%": 0.0
    },
    "kevin bahl": {
        "g": 0.0,
        "a": 0.0,
        "+/-": -1.0,
        "s": 1.0,
        "sm": 1.0,
        "bs": 0.0,
        "pn": 0.0,
        "pim": 0.0,
        "ht": 2.0,
        "tk": 0.0,
        "gv": 2.0,
        "shft": 25.0,
        "toi": 18.33,
        "pptoi": 0.0,
        "shtoi": 3.95,
        "estoi": 14.38,
        "fw": 0.0,
        "fl": 0.0,
        "fo%": 0.0
    },
    "jake bean": {
        "g": 0.0,
        "a": 0.0,
        "+/-": 1.0,
        "s": 1.0,
        "sm": 1.0,
        "bs": 0.0,
        "pn": 0.0,
        "pim": 0.0,
        "ht": 0.0,
        "tk": 0.0,
        "gv": 1.0,
        "shft": 22.0,
        "toi": 16.05,
        "pptoi": 0.28,
        "shtoi": 0.0,
        "estoi": 15.77,
        "fw": 0.0,
        "fl": 0.0,
        "fo%": 0.0
    },
    "daniil miromanov": {
        "g": 0.0,
        "a": 1.0,
        "+/-": 0.0,
        "s": 2.0,
        "sm": 1.0,
        "bs": 0.0,
        "pn": 0.0,
        "pim": 0.0,
        "ht": 1.0,
        "tk": 1.0,
        "gv": 1.0,
        "shft": 20.0,
        "toi": 15.75,
        "pptoi": 0.0,
        "shtoi": 0.23,
        "estoi": 15.52,
        "fw": 0.0,
        "fl": 0.0,
        "fo%": 0.0
    },
    "brayden pachal": {
        "g": 0.0,
        "a": 0.0,
        "+/-": 0.0,
        "s": 0.0,
        "sm": 0.0,
        "bs": 1.0,
        "pn": 0.0,
        "pim": 0.0,
        "ht": 1.0,
        "tk": 0.0,
        "gv": 1.0,
        "shft": 23.0,
        "toi": 15.48,
        "pptoi": 0.45,
        "shtoi": 2.5300000000000002,
        "estoi": 12.5,
        "fw": 0.0,
        "fl": 0.0,
        "fo%": 0.0
    },
    "mackenzie weegar": {
        "g": 1.0,
        "a": 0.0,
        "+/-": 1.0,
        "s": 2.0,
        "sm": 1.0,
        "bs": 2.0,
        "pn": 0.0,
        "pim": 0.0,
        "ht": 3.0,
        "tk": 0.0,
        "gv": 1.0,
        "shft": 30.0,
        "toi": 26.15,
        "pptoi": 4.55,
        "shtoi": 2.67,
        "estoi": 18.93,
        "fw": 0.0,
        "fl": 0.0,
        "fo%": 0.0
    },
    "dustin wolf": {
        "sa": 38.0,
        "ga": 3.0,
        "sv": 35.0,
        "sv%": 0.921,
        "essv": 31.0,
        "ppsv": 3.0,
        "shsv": 1.0,
        "sosa": 0.0,
        "sos": 0.0,
        "toi": 63.92,
        "pim": 0.0
    }
}