{
    "jaren jackson": {
        "min": 29,
        "fgm": 8,
        "fga": 13,
        "3ptm": 3,
        "3pta": 4,
        "ftm": 5,
        "fta": 6,
        "oreb": 0,
        "dreb": 4,
        "reb": 4,
        "ast": 1,
        "stl": 1,
        "blk": 1,
        "to": 1,
        "pf": 4,
        "+/-": 6,
        "pts": 24
    },
    "jaylen wells": {
        "min": 24,
        "fgm": 3,
        "fga": 8,
        "3ptm": 1,
        "3pta": 3,
        "ftm": 4,
        "fta": 4,
        "oreb": 1,
        "dreb": 2,
        "reb": 3,
        "ast": 3,
        "stl": 1,
        "blk": 0,
        "to": 0,
        "pf": 3,
        "+/-": 4,
        "pts": 11
    },
    "zach edey": {
        "min": 27,
        "fgm": 7,
        "fga": 10,
        "3ptm": 0,
        "3pta": 0,
        "ftm": 0,
        "fta": 2,
        "oreb": 5,
        "dreb": 6,
        "reb": 11,
        "ast": 2,
        "stl": 1,
        "blk": 3,
        "to": 1,
        "pf": 4,
        "+/-": 1,
        "pts": 14
    },
    "ja morant": {
        "min": 31,
        "fgm": 9,
        "fga": 23,
        "3ptm": 1,
        "3pta": 5,
        "ftm": 3,
        "fta": 5,
        "oreb": 1,
        "dreb": 7,
        "reb": 8,
        "ast": 10,
        "stl": 1,
        "blk": 0,
        "to": 4,
        "pf": 3,
        "+/-": 0,
        "pts": 22
    },
    "desmond bane": {
        "min": 33,
        "fgm": 12,
        "fga": 18,
        "3ptm": 5,
        "3pta": 8,
        "ftm": 0,
        "fta": 0,
        "oreb": 1,
        "dreb": 3,
        "reb": 4,
        "ast": 6,
        "stl": 2,
        "blk": 0,
        "to": 0,
        "pf": 2,
        "+/-": 2,
        "pts": 29
    },
    "santi aldama": {
        "min": 26,
        "fgm": 4,
        "fga": 10,
        "3ptm": 0,
        "3pta": 4,
        "ftm": 0,
        "fta": 0,
        "oreb": 1,
        "dreb": 4,
        "reb": 5,
        "ast": 2,
        "stl": 0,
        "blk": 0,
        "to": 4,
        "pf": 3,
        "+/-": -7,
        "pts": 8
    },
    "lamar stevens": {
        "min": 8,
        "fgm": 0,
        "fga": 1,
        "3ptm": 0,
        "3pta": 1,
        "ftm": 0,
        "fta": 0,
        "oreb": 0,
        "dreb": 0,
        "reb": 0,
        "ast": 0,
        "stl": 0,
        "blk": 0,
        "to": 1,
        "pf": 1,
        "+/-": -8,
        "pts": 0
    },
    "jay huff": {
        "min": 5,
        "fgm": 0,
        "fga": 0,
        "3ptm": 0,
        "3pta": 0,
        "ftm": 0,
        "fta": 0,
        "oreb": 0,
        "dreb": 0,
        "reb": 0,
        "ast": 0,
        "stl": 0,
        "blk": 0,
        "to": 0,
        "pf": 0,
        "+/-": -8,
        "pts": 0
    },
    "luke kennard": {
        "min": 21,
        "fgm": 0,
        "fga": 0,
        "3ptm": 0,
        "3pta": 0,
        "ftm": 0,
        "fta": 0,
        "oreb": 0,
        "dreb": 0,
        "reb": 0,
        "ast": 2,
        "stl": 0,
        "blk": 0,
        "to": 0,
        "pf": 1,
        "+/-": -9,
        "pts": 0
    },
    "vince williams": {
        "min": 18,
        "fgm": 1,
        "fga": 4,
        "3ptm": 1,
        "3pta": 3,
        "ftm": 0,
        "fta": 0,
        "oreb": 0,
        "dreb": 3,
        "reb": 3,
        "ast": 2,
        "stl": 0,
        "blk": 0,
        "to": 0,
        "pf": 2,
        "+/-": -10,
        "pts": 3
    },
    "scotty pippen": {
        "min": 18,
        "fgm": 6,
        "fga": 8,
        "3ptm": 3,
        "3pta": 4,
        "ftm": 1,
        "fta": 1,
        "oreb": 0,
        "dreb": 3,
        "reb": 3,
        "ast": 5,
        "stl": 1,
        "blk": 0,
        "to": 1,
        "pf": 4,
        "+/-": -6,
        "pts": 16
    },
    "marvin bagley": {},
    "gg jackson": {},
    "john konchar": {},
    "cam spencer": {}
}