{
    "jayson tatum": {
        "min": 42,
        "fgm": 11,
        "fga": 20,
        "3ptm": 4,
        "3pta": 8,
        "ftm": 6,
        "fta": 7,
        "oreb": 2,
        "dreb": 13,
        "reb": 15,
        "ast": 4,
        "stl": 1,
        "blk": 1,
        "to": 3,
        "pf": 2,
        "+/-": 5,
        "pts": 32
    },
    "al horford": {
        "min": 33,
        "fgm": 6,
        "fga": 13,
        "3ptm": 5,
        "3pta": 10,
        "ftm": 0,
        "fta": 0,
        "oreb": 0,
        "dreb": 4,
        "reb": 4,
        "ast": 2,
        "stl": 0,
        "blk": 1,
        "to": 0,
        "pf": 3,
        "+/-": 22,
        "pts": 17
    },
    "kristaps porzingis": {
        "min": 13,
        "fgm": 3,
        "fga": 8,
        "3ptm": 3,
        "3pta": 6,
        "ftm": 0,
        "fta": 0,
        "oreb": 0,
        "dreb": 2,
        "reb": 2,
        "ast": 3,
        "stl": 0,
        "blk": 0,
        "to": 0,
        "pf": 1,
        "+/-": -13,
        "pts": 9
    },
    "derrick white": {
        "min": 33,
        "fgm": 8,
        "fga": 15,
        "3ptm": 5,
        "3pta": 10,
        "ftm": 0,
        "fta": 0,
        "oreb": 0,
        "dreb": 3,
        "reb": 3,
        "ast": 4,
        "stl": 0,
        "blk": 0,
        "to": 4,
        "pf": 3,
        "+/-": -5,
        "pts": 21
    },
    "jaylen brown": {
        "min": 43,
        "fgm": 10,
        "fga": 23,
        "3ptm": 3,
        "3pta": 6,
        "ftm": 0,
        "fta": 3,
        "oreb": 1,
        "dreb": 6,
        "reb": 7,
        "ast": 4,
        "stl": 2,
        "blk": 0,
        "to": 5,
        "pf": 4,
        "+/-": -1,
        "pts": 23
    },
    "sam hauser": {
        "min": 13,
        "fgm": 0,
        "fga": 1,
        "3ptm": 0,
        "3pta": 1,
        "ftm": 0,
        "fta": 0,
        "oreb": 1,
        "dreb": 1,
        "reb": 2,
        "ast": 0,
        "stl": 0,
        "blk": 0,
        "to": 0,
        "pf": 1,
        "+/-": -12,
        "pts": 0
    },
    "luke kornet": {
        "min": 20,
        "fgm": 3,
        "fga": 4,
        "3ptm": 0,
        "3pta": 0,
        "ftm": 0,
        "fta": 1,
        "oreb": 6,
        "dreb": 4,
        "reb": 10,
        "ast": 2,
        "stl": 0,
        "blk": 2,
        "to": 0,
        "pf": 1,
        "+/-": -1,
        "pts": 6
    },
    "neemias queta": {
        "min": 8,
        "fgm": 1,
        "fga": 2,
        "3ptm": 0,
        "3pta": 0,
        "ftm": 0,
        "fta": 0,
        "oreb": 1,
        "dreb": 4,
        "reb": 5,
        "ast": 0,
        "stl": 0,
        "blk": 0,
        "to": 0,
        "pf": 1,
        "+/-": -1,
        "pts": 2
    },
    "payton pritchard": {
        "min": 33,
        "fgm": 1,
        "fga": 9,
        "3ptm": 0,
        "3pta": 8,
        "ftm": 2,
        "fta": 2,
        "oreb": 2,
        "dreb": 1,
        "reb": 3,
        "ast": 5,
        "stl": 0,
        "blk": 0,
        "to": 1,
        "pf": 2,
        "+/-": -12,
        "pts": 4
    },
    "jordan walsh": {
        "min": 1,
        "fgm": 0,
        "fga": 0,
        "3ptm": 0,
        "3pta": 0,
        "ftm": 0,
        "fta": 0,
        "oreb": 0,
        "dreb": 0,
        "reb": 0,
        "ast": 0,
        "stl": 0,
        "blk": 0,
        "to": 0,
        "pf": 0,
        "+/-": -2,
        "pts": 0
    },
    "xavier tillman": {},
    "drew peterson": {},
    "baylor scheierman": {},
    "jd davison": {},
    "jaden springer": {}
}