{
    "world_series": {
        "lad": "+230",
        "atl": "+850",
        "nyy": "+900",
        "nym": "+1100",
        "phi": "+1100",
        "bal": "+1500",
        "bos": "+1800",
        "tex": "+2000",
        "hou": "+2100",
        "sd": "+2500",
        "sea": "+2800",
        "chc": "+3000",
        "ari": "+3000",
        "det": "+3000",
        "min": "+3300",
        "cle": "+4000",
        "kc": "+4000",
        "mil": "+4500",
        "tb": "+5000",
        "tor": "+5500",
        "cin": "+7500",
        "sf": "+9000",
        "stl": "+13000",
        "pit": "+13000",
        "ath": "+20000",
        "laa": "+20000",
        "wsh": "+35000",
        "mia": "+50000",
        "col": "+50000",
        "chw": "+50000"
    },
    "league": {
        "nyy": "+360",
        "bal": "+600",
        "bos": "+700",
        "hou": "+750",
        "tex": "+800",
        "sea": "+1100",
        "det": "+1100",
        "min": "+1100",
        "cle": "+1400",
        "kc": "+1500",
        "tb": "+1800",
        "tor": "+2800",
        "ath": "+7000",
        "laa": "+7000",
        "chw": "+20000",
        "lad": "+135",
        "atl": "+500",
        "nym": "+650",
        "phi": "+650",
        "sd": "+1000",
        "chc": "+1500",
        "ari": "+1600",
        "mil": "+2400",
        "cin": "+3300",
        "sf": "+4300",
        "stl": "+5500",
        "pit": "+7500",
        "wsh": "+9000",
        "mia": "+15000",
        "col": "+20000"
    },
    "team_wins": {
        "ari": {
            "86.5": "-140/+105"
        },
        "ath": {
            "71.5": "-140/+105"
        },
        "atl": {
            "93.5": "-125/-105"
        },
        "bal": {
            "86.5": "-130/100"
        },
        "bos": {
            "86.5": "-140/+105"
        },
        "chc": {
            "86.5": "-105/-125"
        },
        "chw": {
            "54.5": "-125/-105"
        },
        "cin": {
            "79.5": "-145/+110"
        },
        "cle": {
            "82.5": "+110/-150"
        },
        "col": {
            "59.5": "-115/-115"
        },
        "det": {
            "83.5": "-125/-105"
        },
        "hou": {
            "86.5": "-105/-125"
        },
        "kc": {
            "82.5": "-135/+105"
        },
        "laa": {
            "71.5": "-120/-110"
        },
        "lad": {
            "104.5": "-140/+110"
        },
        "mia": {
            "63.5": "100/-130"
        },
        "mil": {
            "83.5": "-125/-105"
        },
        "min": {
            "84.5": "-115/-115"
        },
        "nym": {
            "90.5": "-115/-115"
        },
        "nyy": {
            "88.5": "-120/-110"
        },
        "phi": {
            "90.5": "-115/-115"
        },
        "pit": {
            "75.5": "-130/100"
        },
        "sd": {
            "85.5": "-115/-115"
        },
        "sf": {
            "80.5": "-135/+105"
        },
        "sea": {
            "85.5": "-115/-115"
        },
        "stl": {
            "75.5": "-130/100"
        },
        "tb": {
            "81.5": "-120/-110"
        },
        "tex": {
            "85.5": "-145/+110"
        },
        "tor": {
            "78.5": "-140/+110"
        },
        "wsh": {
            "72.5": "-115/-115"
        }
    },
    "playoffs": {
        "ari": "-130/100",
        "ath": "+550/-1000",
        "atl": "-400/+275",
        "bal": "-180/+135",
        "bos": "-150/+115",
        "chc": "-165/+125",
        "chw": "+3000/-20000",
        "cin": "+210/-300",
        "cle": "+125/-165",
        "col": "+2000/-10000",
        "det": "100/-130",
        "hou": "-165/+125",
        "kc": "+115/-150",
        "laa": "+650/-1400",
        "lad": "-10000/+1400",
        "mia": "+1800/-6000",
        "mil": "-105/-125",
        "min": "+110/-145",
        "nym": "-260/+190",
        "nyy": "-230/+170",
        "phi": "-300/+220",
        "pit": "+380/-600",
        "sd": "-105/-125",
        "sf": "+200/-275",
        "sea": "-105/-125",
        "stl": "+415/-650",
        "tb": "+175/-240",
        "tex": "-150/+115",
        "tor": "+200/-275",
        "wsh": "+775/-1900"
    },
    "k": {
        "brandon pfaadt": {
            "165.5": "-110/-120"
        },
        "corbin burnes": {
            "172.5": "-115/-115",
            "199.5": "+350",
            "249.5": "+1200"
        },
        "zac gallen": {
            "169.5": "-120/-110",
            "199.5": "+425",
            "249.5": "+1300"
        },
        "luis severino": {
            "147.5": "-115/-115"
        },
        "chris sale": {
            "184.5": "-115/-115",
            "199.5": "+145",
            "249.5": "+700"
        },
        "garrett crochet": {
            "201.5": "-115/-115",
            "199.5": "-130",
            "249.5": "+450"
        },
        "tanner houck": {
            "145.5": "-105/-125"
        },
        "hunter greene": {
            "165.5": "-110/-120",
            "199.5": "+250",
            "249.5": "+950"
        },
        "tanner bibee": {
            "169.5": "-115/-115",
            "199.5": "+400",
            "249.5": "+1500"
        },
        "jack flaherty": {
            "159.5": "-115/-115",
            "199.5": "+400"
        },
        "tarik skubal": {
            "204.5": "-110/-120",
            "199.5": "-135",
            "249.5": "+500"
        },
        "hunter brown": {
            "167.5": "-110/-120",
            "199.5": "+400",
            "249.5": "+1300"
        },
        "cole ragans": {
            "192.5": "-105/-125",
            "199.5": "+125",
            "249.5": "+650"
        },
        "yusei kikuchi": {
            "177.5": "-110/-120",
            "199.5": "+250",
            "249.5": "+1000"
        },
        "freddy peralta": {
            "185.5": "-115/-115",
            "199.5": "+170",
            "249.5": "+800"
        },
        "bailey ober": {
            "172.5": "-115/-115"
        },
        "pablo lopez": {
            "183.5": "-110/-120",
            "199.5": "+210",
            "249.5": "+900"
        },
        "paul skenes": {
            "212.5": "100/-130"
        },
        "dylan cease": {
            "205.5": "-110/-120"
        },
        "zack wheeler": {
            "194.5": "-110/-120"
        },
        "blake snell": {
            "199.5": "+140",
            "249.5": "+650"
        },
        "logan gilbert": {
            "189.5": "-125/-105"
        },
        "michael king": {
            "181.5": "-110/-120"
        },
        "carlos rodon": {
            "174.5": "-105/-125"
        },
        "aaron nola": {
            "179.5": "-120/-110"
        },
        "gerrit cole": {
            "199.5": "+300",
            "249.5": "+1100"
        },
        "luis castillo": {
            "172.5": "-115/-115"
        },
        "kevin gausman": {
            "175.5": "-110/-120"
        },
        "grayson rodriguez": {
            "199.5": "+360",
            "249.5": "+1500"
        },
        "kodai senga": {
            "165.5": "-115/-115"
        },
        "yoshinobu yamamoto": {
            "199.5": "+500",
            "249.5": "+1500"
        },
        "roki sasaki": {
            "199.5": "+550",
            "249.5": "+1200"
        },
        "george kirby": {
            "199.5": "+550",
            "249.5": "+1500"
        },
        "logan webb": {
            "161.5": "-110/-120"
        },
        "shota imanaga": {
            "199.5": "+600",
            "249.5": "+2000"
        },
        "luis gil": {
            "199.5": "+625",
            "249.5": "+2000"
        },
        "max fried": {
            "159.5": "-115/-115"
        },
        "sonny gray": {
            "180.5": "100/-130"
        },
        "taj bradley": {
            "Over160.5": "-120/-110"
        },
        "mackenzie gore": {
            "170.5": "-115/-115"
        }
    },
    "w": {
        "brandon pfaadt": {
            "9.5": "-115/-115"
        },
        "corbin burnes": {
            "12.5": "-115/-115"
        },
        "zac gallen": {
            "10.5": "-130/100"
        },
        "jp sears": {
            "9.5": "100/-130"
        },
        "luis severino": {
            "9.5": "-105/-125"
        },
        "chris sale": {
            "12.5": "-125/-105"
        },
        "dean kremer": {
            "8.5": "-110/-120"
        },
        "garrett crochet": {
            "11.5": "-125/-105"
        },
        "hunter greene": {
            "9.5": "-120/-110"
        },
        "ben lively": {
            "8.5": "-115/-115"
        },
        "tanner bibee": {
            "10.5": "-125/-105"
        },
        "jack flaherty": {
            "10.5": "100/-130"
        },
        "tarik skubal": {
            "12.5": "-130/100"
        },
        "framber valdez": {
            "11.5": "-120/-110"
        },
        "hunter brown": {
            "10.5": "-120/-110"
        },
        "cole ragans": {
            "11.5": "100/-130"
        },
        "freddy peralta": {
            "10.5": "-110/-120"
        },
        "bailey ober": {
            "9.5": "-125/-105"
        },
        "pablo lopez": {
            "11.5": "-120/-110"
        },
        "carlos rodon": {
            "10.5": "-125/-105"
        },
        "max fried": {
            "11.5": "-130/100"
        },
        "aaron nola": {
            "11.5": "-115/-115"
        },
        "cristopher sanchez": {
            "10.5": "-125/-105"
        },
        "ranger suarez": {
            "9.5": "-110/-120"
        },
        "zack wheeler": {
            "12.5": "-125/-105"
        },
        "paul skenes": {
            "11.5": "-120/-110"
        },
        "dylan cease": {
            "11.5": "-115/-115"
        },
        "michael king": {
            "10.5": "-130/100"
        },
        "logan webb": {
            "11.5": "-125/-105"
        },
        "logan gilbert": {
            "11.5": "-125/-105"
        },
        "luis castillo": {
            "10.5": "-125/-105"
        },
        "sonny gray": {
            "9.5": "-130/100"
        },
        "kevin gausman": {
            "10.5": "-110/-120"
        },
        "mackenzie gore": {
            "9.5": "-125/-105"
        }
    },
    "h": {
        "corbin carroll": {
            "151.5": "-120/-110"
        },
        "ketel marte": {
            "156.5": "-110/-120",
            "189.5": "+300",
            "199.5": "+400"
        },
        "austin riley": {
            "155.5": "-125/-105"
        },
        "marcell ozuna": {
            "149.5": "-110/-120"
        },
        "matt olson": {
            "147.5": "-110/-120"
        },
        "michael harris": {
            "160.5": "-120/-110"
        },
        "alex bregman": {
            "147.5": "-125/-105"
        },
        "jarren duran": {
            "170.5": "-115/-115"
        },
        "rafael devers": {
            "156.5": "-115/-115",
            "189.5": "+260",
            "199.5": "+360"
        },
        "elly de la cruz": {
            "154.5": "-110/-120",
            "189.5": "+300",
            "199.5": "+380"
        },
        "jose ramirez": {
            "164.5": "-115/-115",
            "189.5": "+240",
            "199.5": "+370",
            "209.5": "+425",
            "219.5": "+900"
        },
        "steven kwan": {
            "165.5": "-110/-120",
            "189.5": "+230",
            "199.5": "+350",
            "209.5": "+400",
            "219.5": "+850"
        },
        "ezequiel tovar": {
            "155.5": "-115/-115"
        },
        "christian walker": {
            "131.5": "-115/-115"
        },
        "yordan alvarez": {
            "153.5": "-120/-110"
        },
        "jackson chourio": {
            "159.5": "-120/-110"
        },
        "luis arraez": {
            "190.5": "-120/-110"
        },
        "bobby witt": {
            "189.5": "+120",
            "199.5": "+190",
            "209.5": "+200",
            "219.5": "+300"
        },
        "vladimir guerrero": {
            "174.5": "-120/-110"
        },
        "trea turner": {
            "161.5": "-125/-105"
        },
        "shohei ohtani": {
            "189.5": "+190",
            "199.5": "+250",
            "209.5": "+350",
            "219.5": "+500"
        },
        "freddie freeman": {
            "189.5": "+200",
            "199.5": "+300",
            "209.5": "+370",
            "219.5": "+650"
        },
        "julio rodriguez": {
            "159.5": "-110/-120"
        },
        "jackson merrill": {
            "157.5": "-125/-105"
        },
        "jose altuve": {
            "189.5": "+240",
            "199.5": "+330",
            "209.5": "+475"
        },
        "mookie betts": {
            "189.5": "+250",
            "199.5": "+350",
            "209.5": "+475"
        },
        "fernando tatis": {
            "147.5": "-115/-115"
        },
        "corey seager": {
            "135.5": "-125/-105"
        },
        "francisco lindor": {
            "157.5": "-110/-120"
        },
        "bryce harper": {
            "146.5": "-110/-120"
        },
        "kyle tucker": {
            "189.5": "+320",
            "199.5": "+450"
        },
        "juan soto": {
            "154.5": "-110/-120"
        },
        "aaron judge": {
            "155.5": "-105/-125"
        },
        "brent rooker": {
            "189.5": "+400"
        },
        "william contreras": {
            "189.5": "+450",
            "199.5": "+700",
            "209.5": "+1100"
        },
        "manny machado": {
            "157.5": "-115/-115"
        }
    },
    "hr": {
        "corbin carroll": {
            "21.5": "-115/-115"
        },
        "eugenio suarez": {
            "24.5": "-125/-105"
        },
        "josh naylor": {
            "23.5": "-120/-110"
        },
        "ketel marte": {
            "26.5": "-115/-115"
        },
        "brent rooker": {
            "33.5": "-125/-105"
        },
        "shea langeliers": {
            "25.5": "-110/-120"
        },
        "austin riley": {
            "31.5": "-125/-105"
        },
        "marcell ozuna": {
            "31.5": "-125/-105"
        },
        "matt olson": {
            "33.5": "-120/-110"
        },
        "michael harris": {
            "19.5": "-125/-105"
        },
        "ozzie albies": {
            "19.5": "-110/-120"
        },
        "adley rutschman": {
            "18.5": "-115/-115"
        },
        "colton cowser": {
            "20.5": "-120/-110"
        },
        "alex bregman": {
            "22.5": "-120/-110"
        },
        "jarren duran": {
            "17.5": "-125/-105"
        },
        "rafael devers": {
            "29.5": "-110/-120"
        },
        "triston casas": {
            "24.5": "-110/-120"
        },
        "elly de la cruz": {
            "24.5": "-135/+105"
        },
        "spencer steer": {
            "19.5": "-115/-115"
        },
        "tyler stephenson": {
            "16.5": "-125/-105"
        },
        "jose ramirez": {
            "29.5": "-125/-105"
        },
        "brenton doyle": {
            "20.5": "-125/-105"
        },
        "ezequiel tovar": {
            "22.5": "-110/-120"
        },
        "michael toglia": {
            "23.5": "-120/-110"
        },
        "ryan mcmahon": {
            "18.5": "-115/-115"
        },
        "kerry carpenter": {
            "21.5": "-120/-110"
        },
        "riley greene": {
            "21.5": "-115/-115"
        },
        "christian walker": {
            "30.5": "100/-130"
        },
        "yordan alvarez": {
            "34.5": "-115/-115"
        },
        "mike trout": {
            "24.5": "-125/-105"
        },
        "taylor ward": {
            "22.5": "-115/-115"
        },
        "william contreras": {
            "23.5": "-120/-110"
        },
        "francisco lindor": {
            "27.5": "-105/-125"
        },
        "juan soto": {
            "34.5": "-115/-115"
        },
        "mark vientos": {
            "28.5": "-115/-115"
        },
        "pete alonso": {
            "34.5": "-125/-105"
        },
        "aaron judge": {
            "48.5": "-110/-120"
        },
        "cody bellinger": {
            "21.5": "-110/-120"
        },
        "jazz chisholm": {
            "21.5": "-115/-115"
        },
        "paul goldschmidt": {
            "21.5": "-110/-120"
        },
        "alec bohm": {
            "16.5": "-115/-115"
        },
        "bryce harper": {
            "27.5": "-115/-115"
        },
        "kyle schwarber": {
            "35.5": "-115/-115"
        },
        "trea turner": {
            "19.5": "-115/-115"
        },
        "oneil cruz": {
            "22.5": "-130/100"
        },
        "fernando tatis": {
            "30.5": "-115/-115"
        },
        "jackson merrill": {
            "24.5": "-110/-120"
        },
        "manny machado": {
            "29.5": "-120/-110"
        },
        "cal raleigh": {
            "30.5": "100/-130"
        },
        "julio rodriguez": {
            "26,5": "-110/-120"
        },
        "nolan arenado": {
            "17.5": "-115/-115"
        },
        "wilson contreras": {
            "19.5": "-120/-110"
        },
        "corey seager": {
            "28.5": "-125/-105"
        },
        "jake burger": {
            "26.5": "-125/-105"
        },
        "joc pederson": {
            "20.5": "-115/-115"
        },
        "marcus semien": {
            "22.5": "-110/-120"
        },
        "anthony santander": {
            "31.5": "-115/-115"
        },
        "vladimir guerrero": {
            "31.5": "-120/-110"
        },
        "cj abrams": {
            "17.5": "-115/-115"
        },
        "james wood": {
            "18.5": "100/-130"
        }
    },
    "rbi": {
        "corbin carroll": {
            "74.5": "-115/-115"
        },
        "eugenio suarez": {
            "81.5": "-115/-115"
        },
        "josh naylor": {
            "90.5": "-115/-115"
        },
        "ketel marte": {
            "85.5": "-115/-115",
            "119.5": "+475",
            "129.5": "+850"
        },
        "brent rooker": {
            "93.5": "-105/-125",
            "119.5": "+280",
            "129.5": "+500",
            "139.5": "+900",
            "149.5": "+1700"
        },
        "shea langeliers": {
            "73.5": "-105/-125"
        },
        "austin riley": {
            "90.5": "-120/-110",
            "119.5": "+320",
            "129.5": "+550",
            "139.5": "+1000",
            "149.5": "+2000"
        },
        "marcell ozuna": {
            "91.5": "-125/-105",
            "119.5": "+320",
            "129.5": "+550",
            "139.5": "+1000",
            "149.5": "+2000"
        },
        "matt olson": {
            "94.5": "-120/-110",
            "119.5": "+210",
            "129.5": "+370",
            "139.5": "+650",
            "149.5": "+1200"
        },
        "michael harris": {
            "70.5": "-115/-115"
        },
        "ozzie albies": {
            "79.5": "-115/-115"
        },
        "adley rutschman": {
            "70.5": "-120/-110"
        },
        "colton cowser": {
            "67.5": "-115/-115"
        },
        "alex bregman": {
            "79.5": "-125/-105"
        },
        "jarren duran": {
            "73.5": "-110/-120"
        },
        "rafael devers": {
            "92.5": "-120/-110",
            "119.5": "+270",
            "129.5": "+450",
            "139.5": "+850",
            "149.5": "+1600"
        },
        "triston casas": {
            "75.5": "-115/-115"
        },
        "elly de la cruz": {
            "77.5": "-115/-115",
            "119.5": "+650"
        },
        "spencer steer": {
            "75.5": "-105/-125"
        },
        "jose ramirez": {
            "97.5": "-115/-115",
            "119.5": "+240",
            "129.5": "+425",
            "139.5": "+750",
            "149.5": "+1400"
        },
        "brenton doyle": {
            "72.5": "-105/-125"
        },
        "ezequiel tovar": {
            "80.5": "-115/-115",
            "119.5": "+650"
        },
        "michael toglia": {
            "69.5": "-125/-105"
        },
        "ryan mcmahon": {
            "65.5": "-115/-115"
        },
        "kerry carpenter": {
            "70.5": "-110/-120"
        },
        "riley greene": {
            "76.5": "-115/-115"
        },
        "christian walker": {
            "88.5": "-105/-125",
            "119.5": "+370",
            "129.5": "+700",
            "139.5": "+1200"
        },
        "yordan alvarez": {
            "101.5": "-105/-125",
            "119.5": "+240",
            "129.5": "+400",
            "139.5": "+700",
            "149.5": "+1300"
        },
        "taylor ward": {
            "72.5": "-115/-115"
        },
        "william contreras": {
            "82.5": "-130/100",
            "119.5": "+650"
        },
        "aaron judge": {
            "110.5": "-105/-125"
        },
        "shohei ohtani": {
            "119.5": "+110",
            "129.5": "+185",
            "139.5": "+300",
            "149.5": "+550"
        },
        "vladimir guerrero": {
            "97.5": "-125/-105"
        },
        "pete alonso": {
            "99.5": "-115/-115"
        },
        "anthony santander": {
            "119.5": "+250",
            "129.5": "+450",
            "139.5": "+800",
            "149.5": "+1500"
        },
        "bobby witt": {
            "119.5": "+270",
            "129.5": "+450",
            "139.5": "+850",
            "149.5": "+1600"
        },
        "teoscar hernandez": {
            "119.5": "+280",
            "129.5": "+500",
            "139.5": "+900",
            "149.5": "+1700"
        },
        "juan soto": {
            "102.5": "-115/-115"
        },
        "manny machado": {
            "94.5": "-115/-115"
        },
        "kyle schwarber": {
            "90.5": "-115/-115"
        },
        "fernando tatis": {
            "90.5": "-120/-110"
        },
        "gunnar henderson": {
            "119.5": "+350",
            "129.5": "+650",
            "139.5": "+1200"
        },
        "bryce harper": {
            "90.5": "-110/-120"
        },
        "kyle tucker": {
            "119.5": "+370",
            "129.5": "+700",
            "139.5": "+1200"
        },
        "mookie betts": {
            "119.5": "+400",
            "129.5": "+750",
            "139.5": "+1400"
        },
        "mark vientos": {
            "86.5": "-110/-120"
        },
        "freddie freeman": {
            "119.5": "+400",
            "129.5": "+700",
            "139.5": "+1300"
        },
        "julio rodriguez": {
            "119.5": "+450",
            "129.5": "+800"
        },
        "jackson merrill": {
            "119.5": "+475",
            "129.5": "+850"
        },
        "salvador perez": {
            "119.5": "+500",
            "129.5": "+900"
        },
        "francisco lindor": {
            "89.5": "-105/-125"
        },
        "adolis garcia": {
            "119.5": "+550",
            "129.5": "+1000"
        },
        "vinnie pasquantino": {
            "119.5": "+550",
            "129.5": "+950"
        },
        "jake burger": {
            "119.5": "+550",
            "129.5": "+950"
        },
        "cal raleigh": {
            "119.5": "+600",
            "129.5": "+1100"
        },
        "willy adames": {
            "119.5": "+600",
            "129.5": "+1100"
        },
        "jackson chourio": {
            "119.5": "+600",
            "129.5": "+1100"
        },
        "corey seager": {
            "83.5": "-125/-105"
        },
        "bryan reynolds": {
            "119.5": "+650"
        },
        "nick castellanos": {
            "119.5": "+650"
        },
        "junior caminero": {
            "119.5": "+650"
        },
        "wyatt langford": {
            "119.5": "+700"
        },
        "oneil cruz": {
            "119.5": "+700"
        },
        "jazz chisholm": {
            "68.5": "-115/-115"
        },
        "cody bellinger": {
            "69.5": "-115/-115"
        },
        "paul goldschmidt": {
            "69.5": "-115/-115"
        },
        "alec bohm": {
            "79.5": "-125/-105"
        },
        "trea turner": {
            "78.5": "-115/-115"
        },
        "nolan arenado": {
            "70.5": "-115/-115"
        },
        "wilson contreras": {
            "58.5": "-120/-110"
        },
        "cj abrams": {
            "65.5": "-115/-115"
        },
        "james wood": {
            "65.5": "-130/100"
        }
    },
    "sb": {
        "corbin carroll": {
            "38.5": "-125/-105"
        },
        "jarren duran": {
            "29.5": "-130/100"
        },
        "elly de la cruz": {
            "54.5": "-115/-115"
        },
        "spencer steer": {
            "19.5": "100/-130"
        },
        "jose ramirez": {
            "29.5": "-125/-105"
        },
        "xavier edwards": {
            "32.5": "-120/-110"
        },
        "brice turang": {
            "36.5": "-125/-110"
        },
        "francisco lindor": {
            "25.5": "-110/-120"
        },
        "anthony volpe": {
            "26.5": "-120/-110"
        },
        "jazz chisholm": {
            "33.5": "-130/100"
        },
        "trea turner": {
            "22.5": "-115/-115"
        },
        "oneil cruz": {
            "20.5": "-130/100"
        },
        "fernando tatis": {
            "21.5": "-110/-120"
        },
        "julio rodriguez": {
            "26.5": "-120/-110"
        },
        "victor robles": {
            "31.5": "-125/-105"
        },
        "cj abrams": {
            "34.5": "-105/-125"
        },
        "james wood": {
            "18.5": "-115/-115"
        }
    },
    "era": {
        "aaron nola": {
            "3.75": "-115/-115"
        },
        "dylan cease": {
            "3.40": "-120/-110"
        },
        "kevin gausman": {
            "3.80": "-115/-115"
        }
    }
}