{
    "pascal siakam": {
        "min": 30,
        "fgm": 12,
        "fga": 16,
        "3ptm": 1,
        "3pta": 4,
        "ftm": 0,
        "fta": 2,
        "oreb": 3,
        "dreb": 6,
        "reb": 9,
        "ast": 0,
        "stl": 1,
        "blk": 0,
        "to": 1,
        "pf": 1,
        "+/-": 21,
        "pts": 25
    },
    "myles turner": {
        "min": 29,
        "fgm": 3,
        "fga": 9,
        "3ptm": 1,
        "3pta": 4,
        "ftm": 4,
        "fta": 6,
        "oreb": 0,
        "dreb": 8,
        "reb": 8,
        "ast": 2,
        "stl": 1,
        "blk": 3,
        "to": 1,
        "pf": 2,
        "+/-": 21,
        "pts": 11
    },
    "andrew nembhard": {
        "min": 29,
        "fgm": 2,
        "fga": 6,
        "3ptm": 0,
        "3pta": 0,
        "ftm": 0,
        "fta": 2,
        "oreb": 2,
        "dreb": 2,
        "reb": 4,
        "ast": 5,
        "stl": 1,
        "blk": 0,
        "to": 1,
        "pf": 1,
        "+/-": 12,
        "pts": 4
    },
    "tyrese haliburton": {
        "min": 35,
        "fgm": 8,
        "fga": 10,
        "3ptm": 2,
        "3pta": 4,
        "ftm": 7,
        "fta": 7,
        "oreb": 0,
        "dreb": 2,
        "reb": 2,
        "ast": 10,
        "stl": 3,
        "blk": 0,
        "to": 5,
        "pf": 1,
        "+/-": 18,
        "pts": 25
    },
    "bennedict mathurin": {
        "min": 34,
        "fgm": 9,
        "fga": 18,
        "3ptm": 3,
        "3pta": 8,
        "ftm": 0,
        "fta": 0,
        "oreb": 1,
        "dreb": 9,
        "reb": 10,
        "ast": 2,
        "stl": 0,
        "blk": 0,
        "to": 2,
        "pf": 2,
        "+/-": 22,
        "pts": 21
    },
    "james johnson": {
        "min": 2,
        "fgm": 0,
        "fga": 0,
        "3ptm": 0,
        "3pta": 0,
        "ftm": 0,
        "fta": 0,
        "oreb": 0,
        "dreb": 0,
        "reb": 0,
        "ast": 0,
        "stl": 0,
        "blk": 0,
        "to": 0,
        "pf": 1,
        "+/-": -5,
        "pts": 0
    },
    "obi toppin": {
        "min": 16,
        "fgm": 1,
        "fga": 3,
        "3ptm": 0,
        "3pta": 2,
        "ftm": 0,
        "fta": 0,
        "oreb": 0,
        "dreb": 4,
        "reb": 4,
        "ast": 1,
        "stl": 0,
        "blk": 2,
        "to": 1,
        "pf": 1,
        "+/-": -4,
        "pts": 2
    },
    "jarace walker": {
        "min": 7,
        "fgm": 0,
        "fga": 3,
        "3ptm": 0,
        "3pta": 0,
        "ftm": 0,
        "fta": 0,
        "oreb": 1,
        "dreb": 2,
        "reb": 3,
        "ast": 0,
        "stl": 0,
        "blk": 0,
        "to": 1,
        "pf": 1,
        "+/-": -9,
        "pts": 0
    },
    "johnny furphy": {
        "min": 2,
        "fgm": 0,
        "fga": 0,
        "3ptm": 0,
        "3pta": 0,
        "ftm": 0,
        "fta": 0,
        "oreb": 0,
        "dreb": 0,
        "reb": 0,
        "ast": 0,
        "stl": 0,
        "blk": 0,
        "to": 0,
        "pf": 0,
        "+/-": -5,
        "pts": 0
    },
    "thomas bryant": {
        "min": 17,
        "fgm": 2,
        "fga": 3,
        "3ptm": 1,
        "3pta": 2,
        "ftm": 0,
        "fta": 0,
        "oreb": 1,
        "dreb": 3,
        "reb": 4,
        "ast": 1,
        "stl": 2,
        "blk": 2,
        "to": 0,
        "pf": 0,
        "+/-": -4,
        "pts": 5
    },
    "tj mcconnell": {
        "min": 17,
        "fgm": 4,
        "fga": 8,
        "3ptm": 0,
        "3pta": 0,
        "ftm": 2,
        "fta": 2,
        "oreb": 0,
        "dreb": 2,
        "reb": 2,
        "ast": 6,
        "stl": 0,
        "blk": 1,
        "to": 2,
        "pf": 1,
        "+/-": 5,
        "pts": 10
    },
    "rayj dennis": {
        "min": 2,
        "fgm": 0,
        "fga": 0,
        "3ptm": 0,
        "3pta": 0,
        "ftm": 0,
        "fta": 0,
        "oreb": 0,
        "dreb": 0,
        "reb": 0,
        "ast": 0,
        "stl": 0,
        "blk": 0,
        "to": 1,
        "pf": 0,
        "+/-": -5,
        "pts": 0
    },
    "ben sheppard": {
        "min": 20,
        "fgm": 2,
        "fga": 6,
        "3ptm": 1,
        "3pta": 3,
        "ftm": 0,
        "fta": 0,
        "oreb": 0,
        "dreb": 2,
        "reb": 2,
        "ast": 0,
        "stl": 0,
        "blk": 0,
        "to": 0,
        "pf": 2,
        "+/-": -7,
        "pts": 5
    },
    "aaron nesmith": {}
}