{
    "jeremy sochan": {
        "min": 42,
        "fgm": 8,
        "fga": 14,
        "3ptm": 1,
        "3pta": 2,
        "ftm": 3,
        "fta": 5,
        "oreb": 2,
        "dreb": 6,
        "reb": 8,
        "ast": 4,
        "stl": 1,
        "blk": 2,
        "to": 1,
        "pf": 4,
        "+/-": 5,
        "pts": 20
    },
    "harrison barnes": {
        "min": 18,
        "fgm": 2,
        "fga": 9,
        "3ptm": 0,
        "3pta": 4,
        "ftm": 2,
        "fta": 3,
        "oreb": 1,
        "dreb": 2,
        "reb": 3,
        "ast": 2,
        "stl": 1,
        "blk": 0,
        "to": 1,
        "pf": 2,
        "+/-": 8,
        "pts": 6
    },
    "victor wembanyama": {
        "min": 37,
        "fgm": 13,
        "fga": 24,
        "3ptm": 7,
        "3pta": 15,
        "ftm": 9,
        "fta": 12,
        "oreb": 0,
        "dreb": 6,
        "reb": 6,
        "ast": 5,
        "stl": 2,
        "blk": 4,
        "to": 5,
        "pf": 0,
        "+/-": 17,
        "pts": 42
    },
    "chris paul": {
        "min": 32,
        "fgm": 4,
        "fga": 4,
        "3ptm": 3,
        "3pta": 3,
        "ftm": 1,
        "fta": 1,
        "oreb": 0,
        "dreb": 7,
        "reb": 7,
        "ast": 8,
        "stl": 4,
        "blk": 1,
        "to": 4,
        "pf": 1,
        "+/-": 17,
        "pts": 12
    },
    "devin vassell": {
        "min": 38,
        "fgm": 9,
        "fga": 16,
        "3ptm": 5,
        "3pta": 7,
        "ftm": 0,
        "fta": 0,
        "oreb": 1,
        "dreb": 3,
        "reb": 4,
        "ast": 2,
        "stl": 2,
        "blk": 0,
        "to": 1,
        "pf": 1,
        "+/-": 4,
        "pts": 23
    },
    "julian champagnie": {
        "min": 26,
        "fgm": 3,
        "fga": 8,
        "3ptm": 2,
        "3pta": 6,
        "ftm": 0,
        "fta": 0,
        "oreb": 0,
        "dreb": 4,
        "reb": 4,
        "ast": 2,
        "stl": 2,
        "blk": 0,
        "to": 1,
        "pf": 3,
        "+/-": 4,
        "pts": 8
    },
    "keldon johnson": {
        "min": 29,
        "fgm": 5,
        "fga": 9,
        "3ptm": 1,
        "3pta": 2,
        "ftm": 0,
        "fta": 0,
        "oreb": 2,
        "dreb": 3,
        "reb": 5,
        "ast": 4,
        "stl": 2,
        "blk": 0,
        "to": 2,
        "pf": 0,
        "+/-": 5,
        "pts": 11
    },
    "charles bassey": {
        "min": 8,
        "fgm": 2,
        "fga": 5,
        "3ptm": 0,
        "3pta": 0,
        "ftm": 0,
        "fta": 0,
        "oreb": 2,
        "dreb": 2,
        "reb": 4,
        "ast": 0,
        "stl": 0,
        "blk": 1,
        "to": 1,
        "pf": 1,
        "+/-": -7,
        "pts": 4
    },
    "tre jones": {
        "min": 14,
        "fgm": 0,
        "fga": 2,
        "3ptm": 0,
        "3pta": 1,
        "ftm": 0,
        "fta": 0,
        "oreb": 0,
        "dreb": 0,
        "reb": 0,
        "ast": 2,
        "stl": 0,
        "blk": 0,
        "to": 0,
        "pf": 1,
        "+/-": -2,
        "pts": 0
    },
    "stephon castle": {
        "min": 21,
        "fgm": 3,
        "fga": 10,
        "3ptm": 0,
        "3pta": 2,
        "ftm": 1,
        "fta": 2,
        "oreb": 0,
        "dreb": 1,
        "reb": 1,
        "ast": 3,
        "stl": 1,
        "blk": 0,
        "to": 1,
        "pf": 2,
        "+/-": -16,
        "pts": 7
    },
    "zach collins": {},
    "sandro mamukelashvili": {},
    "malaki branham": {},
    "blake wesley": {},
    "sidy cissoko": {}
}